fastapi_easy_versioning/__init__.py
fastapi_easy_versioning/dependency.py
fastapi_easy_versioning/middleware.py
fastapi_easy_versioning/py.typed
fastapi_easy_versioning-0.2.0.dist-info/WHEEL
fastapi_easy_versioning-0.2.0.dist-info/METADATA
fastapi_easy_versioning-0.2.0.dist-info/RECORD
