Metadata-Version: 2.3
Name: fastapi-easy-versioning
Version: 0.2.0
Summary: Easy way to build versioning APIs by FastAPI
Author: Fedor Ratschew
Author-email: Fedor Ratschew <feodor.ra@me.com>
License: MIT License
Classifier: Development Status :: 5 - Production/Stable
Classifier: Framework :: FastAPI
Classifier: Intended Audience :: Developers
Classifier: License :: OSI Approved :: MIT License
Classifier: Programming Language :: Python :: 3.10
Classifier: Programming Language :: Python :: 3.11
Classifier: Programming Language :: Python :: 3.12
Classifier: Programming Language :: Python :: 3.13
Classifier: Programming Language :: Python :: 3.9
Classifier: Topic :: Utilities
Classifier: Typing :: Typed
Requires-Dist: fastapi>=0.95.0
Requires-Python: >=3.9.0, <4
Project-URL: Documentation, https://feodor-ra.github.io/fastapi-easy-versioning/
Project-URL: Homepage, https://github.com/feodor-ra/fastapi-easy-versioning
Project-URL: Repository, https://github.com/feodor-ra/fastapi-easy-versioning
